{"candidates":[{"id":"...","firstName":"Manuel","lastName":"Muster","phoneNumber":"0799999999","dateOfBirth":"YYYY-MM-DDTHH:MM:SS.SSSZ","imageUrlLarge":"","imageUrlMedium":"","imageUrlSmall":"","salutation":"","country":"Switzerland","city":"Z端rich","nationality":{"id":171,"name":"Swiss"},"residencePermit":{"id":1,"name":"Swiss"},"onboardingState":"finished","jobRequirement":{"id":16,"startDate":"YYYY-MM-DDTHH:MM:SS.SSSZ","careerGoal":"Striking a balance between learning new skills, and applying as well as improving the ones I have.","positionRequirements":"","desiredJobType":{"id":1,"name":"Full-time"},"desiredWorkArea":{"id":2,"name":"Zurich area"},"desiredTravelActivity":{"id":1,"name":"Rarely"},"interests":[{"id":3,"name":"Artificial Inteligence"},{"id":1,"name":"Algorithms"},{"id":8,"name":"Computer Vision"},{"id":10,"name":"Data Science"},{"id":11,"name":"Digitalization"},{"id":24,"name":"Research & Development"},{"id":26,"name":"Software Development"}]},"education":[{"id":24,"university":{"id":2,"name":"ETH Z端rich"},"otherUniversity":"","educationLevel":{"id":1,"name":"Ph.D."},"startDate":"YYYY-MM-DDTHH:MM:SS.SSSZ","endDate":"YYYY-MM-DDTHH:MM:SS.SSSZ","major":{"id":35,"name":"Mathematics"},"otherMajor":"","averageGrade":5.63,"specialization":null,"otherSpecialization":"","theses":[]},{"id":35,"university":{"id":3,"name":"University of Z端rich"},"otherUniversity":"","educationLevel":{"id":4,"name":"Bachelor"},"startDate":"YYYY-MM-DDTHH:MM:SS.SSSZ","endDate":"YYYY-MM-DDTHH:MM:SS.SSSZ","major":{"id":35,"name":"Mathematics"},"otherMajor":"","averageGrade":5.6,"specialization":null,"otherSpecialization":"","theses":[]},{"id":34,"university":{"id":3,"name":"University of Z端rich"},"otherUniversity":"","educationLevel":{"id":2,"name":"Master"},"startDate":"YYYY-MM-DDTHH:MM:SS.SSSZ","endDate":"YYYY-MM-DDTHH:MM:SS.SSSZ","major":{"id":35,"name":"Mathematics"},"otherMajor":"","averageGrade":5.7,"specialization":{"id":21,"name":"Statistics"},"otherSpecialization":"","theses":[]}],"experiences":[{"id":20,"title":"Mathematics Teacher (Subsitute)","employer":"Kantonsschule","jobType":{"id":1,"name":"Full-time"},"startDate":"YYYY-MM-DDTHH:MM:SS.SSSZ","endDate":"YYYY-MM-DDTHH:MM:SS.SSSZ","description":""},{"id":21,"title":"Teaching Assistant","employer":"ETH Zurich","jobType":{"id":1,"name":"Full-time"},"startDate":"YYYY-MM-DDTHH:MM:SS.SSSZ","endDate":"YYYY-MM-DDTHH:MM:SS.SSSZ","description":"text description."},{"id":18,"title":"Graduate Trainee","employer":"employer name","jobType":{"id":1,"name":"Full-time"},"startDate":"YYYY-MM-DDTHH:MM:SS.SSSZ","endDate":"YYYY-MM-DDTHH:MM:SS.SSSZ","description":"description text."},{"id":19,"title":"title text","employer":"employer text","jobType":{"id":2,"name":"Part-time"},"startDate":"YYYY-MM-DDTHH:MM:SS.SSSZ","endDate":"YYYY-MM-DDTHH:MM:SS.SSSZ","description":"description text"}],"extracurriculars":[],"languages":[{"id":866,"languageLevel":{"id":4,"name":"Native"},"language":{"code":"DE","name":"German"},"qualification":"Native speaker in both Swiss German and German."},{"id":867,"languageLevel":{"id":3,"name":"Fluent"},"language":{"code":"EN","name":"English"},"qualification":"used daily in the international work environment of ETH"}],"itSkills":[{"id":1344,"itSkill":{"id":8,"name":"Latex"},"otherItSkill":null,"skillLevel":{"id":2,"name":"Intermediate"},"description":"used for my theses"},{"id":1345,"itSkill":{"id":10,"name":"MATLAB"},"otherItSkill":null,"skillLevel":{"id":1,"name":"Beginner"},"description":" used during my Bachelor's"},{"id":1346,"itSkill":{"id":11,"name":"Office Tools"},"otherItSkill":null,"skillLevel":{"id":2,"name":"Intermediate"},"description":"text"},{"id":1347,"itSkill":{"id":14,"name":"Python"},"otherItSkill":null,"skillLevel":{"id":1,"name":"Beginner"},"description":"successfully completed the course \"Python for Data Science and Machine Learning\""},{"id":1348,"itSkill":{"id":17,"name":"Other"},"otherItSkill":"Shell","skillLevel":{"id":1,"name":"Beginner"},"description":" used at Statistik .."},{"id":1349,"itSkill":{"id":17,"name":"Other"},"otherItSkill":"SPSS","skillLevel":{"id":1,"name":"Beginner"},"description":"text"},{"id":1350,"itSkill":{"id":17,"name":"Other"},"otherItSkill":"VBA","skillLevel":{"id":1,"name":"Beginner"},"description":"text"}],"miscs":null,"registrationDate":"..."},
